xltables.py
xltables_for_openpyxl_uod-1.1.1.dist-info/LICENSE.txt
xltables_for_openpyxl_uod-1.1.1.dist-info/METADATA
xltables_for_openpyxl_uod-1.1.1.dist-info/WHEEL
xltables_for_openpyxl_uod-1.1.1.dist-info/top_level.txt
xltables_for_openpyxl_uod-1.1.1.dist-info/RECORD
